nobinobi_kitchen/__init__.py
nobinobi_kitchen/apps.py
nobinobi_kitchen/forms.py
nobinobi_kitchen/menus.py
nobinobi_kitchen/signals.py
nobinobi_kitchen/urls.py
nobinobi_kitchen/utils.py
nobinobi_kitchen/views.py
nobinobi_kitchen/locale/en/LC_MESSAGES/django.po
nobinobi_kitchen/locale/fr/LC_MESSAGES/django.mo
nobinobi_kitchen/locale/fr/LC_MESSAGES/django.po
nobinobi_kitchen/static/css/nobinobi_kitchen.css
nobinobi_kitchen/static/img/.gitignore
nobinobi_kitchen/static/js/nobinobi_kitchen.js
nobinobi_kitchen/templates/nobinobi_kitchen/kitchen_select.html
nobinobi_kitchen/templates/nobinobi_kitchen/kitchen_view.html
nobinobi_kitchen/templates/nobinobi_kitchen/kitchen_view2.html
nobinobi_kitchen/templatetags/__init__.py
nobinobi_kitchen/templatetags/kitchen_tags.py
nobinobi_kitchen-0.1.1.dist-info/AUTHORS.rst
nobinobi_kitchen-0.1.1.dist-info/LICENSE
nobinobi_kitchen-0.1.1.dist-info/METADATA
nobinobi_kitchen-0.1.1.dist-info/WHEEL
nobinobi_kitchen-0.1.1.dist-info/top_level.txt
nobinobi_kitchen-0.1.1.dist-info/RECORD
