Metadata-Version: 2.1
Name: nobinobi-kitchen
Version: 0.1.1
Summary: Application Kitchen for Nobinobi
Home-page: https://github.com/prolibre-ch/nobinobi-kitchen
Author: Florian Alu
Author-email: alu@prolibre.com
License: UNKNOWN
Keywords: nobinobi-kitchen
Platform: UNKNOWN
Classifier: Development Status :: 3 - Alpha
Classifier: Framework :: Django :: 3.2
Classifier: Intended Audience :: Developers
Classifier: License :: OSI Approved :: GNU Affero General Public License v3 or later (AGPLv3+)
Classifier: Natural Language :: English
Classifier: Programming Language :: Python :: 3
Classifier: Programming Language :: Python :: 3.6
Classifier: Programming Language :: Python :: 3.7
Classifier: Programming Language :: Python :: 3.8
License-File: LICENSE
License-File: AUTHORS.rst
Requires-Dist: nobinobi-daily-follow-up (>=0.1.1.13)
